fxencoder_plusplus/__init__.py
fxencoder_plusplus/model.py
fxencoder_plusplus-0.1.5.dist-info/licenses/LICENSE
fxencoder_plusplus-0.1.5.dist-info/METADATA
fxencoder_plusplus-0.1.5.dist-info/WHEEL
fxencoder_plusplus-0.1.5.dist-info/top_level.txt
fxencoder_plusplus-0.1.5.dist-info/RECORD
