Metadata-Version: 2.4
Name: fxencoder_plusplus
Version: 0.1.5
Summary: Fx-Encoder++ for audio effects representation
Home-page: https://github.com/SonyResearch/Fx-Encoder_PlusPlus
Author: ytsrt66589
Author-email: ytsrt66589@gmail.com
License: CC BY-NC 4.0
License-File: LICENSE
Requires-Dist: torch
Requires-Dist: numpy
Requires-Dist: laion-clap
Requires-Dist: torchlibrosa
Requires-Dist: huggingface_hub
Dynamic: author
Dynamic: author-email
Dynamic: description
Dynamic: description-content-type
Dynamic: home-page
Dynamic: license
Dynamic: license-file
Dynamic: requires-dist
Dynamic: summary
